pyblocksim/__init__.py
pyblocksim/core.py
pyblocksim/release.py
pyblocksim/td.py
pyblocksim-0.3.3.dist-info/COPYING.gpl3
pyblocksim-0.3.3.dist-info/LICENSE
pyblocksim-0.3.3.dist-info/METADATA
pyblocksim-0.3.3.dist-info/WHEEL
pyblocksim-0.3.3.dist-info/top_level.txt
pyblocksim-0.3.3.dist-info/RECORD
