Metadata-Version: 2.1
Name: pyblocksim
Version: 0.3.3
Summary: Python library for block-oriented modeling and simulation in control theory
Author-email: Carsten Knoll <firstname.lastname@tu-dresden.de>
License: GNU General Public License v3 (GPLv3)
Project-URL: Homepage, https://github.com/TUD-RST/pyblocksim
Classifier: Development Status :: 4 - Beta
Classifier: Intended Audience :: Developers
Classifier: Programming Language :: Python :: 3
Requires-Python: >=3.8
License-File: LICENSE
License-File: COPYING.gpl3
Requires-Dist: sympy >=1.0
Requires-Dist: scipy >=1.0
Requires-Dist: ipydex >=0.1.2
Requires-Dist: matplotlib
Requires-Dist: symbtools
